LICENCE.txt
README.md
setup.py
pysnmp_sync_adapter/__init__.py
pysnmp_sync_adapter/__version__.py
pysnmp_sync_adapter/cmdgen_wrappers.py
pysnmp_sync_adapter/legacy_wrappers.py
pysnmp_sync_adapter/sync_adapters.py
pysnmp_sync_adapter.egg-info/PKG-INFO
pysnmp_sync_adapter.egg-info/SOURCES.txt
pysnmp_sync_adapter.egg-info/dependency_links.txt
pysnmp_sync_adapter.egg-info/requires.txt
pysnmp_sync_adapter.egg-info/top_level.txt
tests/test_pysnmp_sync_v1arch.py
tests/test_pysnmp_sync_v3arch.py