Metadata-Version: 2.4
Name: pysnmp-sync-adapter
Version: 1.0.8
Summary: Lightweight Synchronous wrapper adapters for PySNMP AsyncIO HLAPI
Author: Ircama
License: EUPL-1.2
Project-URL: Homepage, https://github.com/Ircama/pysnmp-sync-adapter
Project-URL: Repository, https://github.com/Ircama/pysnmp-sync-adapter
Keywords: snmp synchronous pysnmp
Classifier: Programming Language :: Python :: 3
Classifier: License :: OSI Approved :: European Union Public Licence 1.2 (EUPL 1.2)
Classifier: Topic :: Software Development :: Libraries :: Python Modules
Classifier: Operating System :: OS Independent
Classifier: Development Status :: 5 - Production/Stable
Classifier: Intended Audience :: Developers
Requires-Python: >=3.7
License-File: LICENCE.txt
Requires-Dist: pysnmp>=7.0.0
Dynamic: author
Dynamic: classifier
Dynamic: description
Dynamic: description-content-type
Dynamic: keywords
Dynamic: license
Dynamic: license-file
Dynamic: project-url
Dynamic: requires-dist
Dynamic: requires-python
Dynamic: summary
